topsis/_102203551.py
topsis/__init__.py
topsis/__main__.py
102203551_topsis-1.0.5.dist-info/LICENSE
102203551_topsis-1.0.5.dist-info/METADATA
102203551_topsis-1.0.5.dist-info/WHEEL
102203551_topsis-1.0.5.dist-info/entry_points.txt
102203551_topsis-1.0.5.dist-info/top_level.txt
102203551_topsis-1.0.5.dist-info/RECORD
